hanimetv/__init__.py
hanimetv/api.py
hanimetv/cli.py
hanimetv-1.2.1.dist-info/entry_points.txt
hanimetv-1.2.1.dist-info/WHEEL
hanimetv-1.2.1.dist-info/METADATA
hanimetv-1.2.1.dist-info/RECORD
