Metadata-Version: 2.1
Name: hanimetv
Version: 1.2.1
Summary: CLI downloader tool for hanime.tv
Home-page: https://github.com/rxqv/htv
Author: rxqv
Requires-Python: >=3.6,<4.0
Classifier: Programming Language :: Python :: 3
Classifier: Programming Language :: Python :: 3.6
Classifier: Programming Language :: Python :: 3.7
Classifier: Programming Language :: Python :: 3.8
Classifier: Programming Language :: Python :: 3.9
Requires-Dist: requests
Requires-Dist: youtube_dl
Project-URL: Repository, https://github.com/rxqv/htv
